mipi_datamanager/__init__.py
mipi_datamanager/connection.py
mipi_datamanager/core/__init__.py
mipi_datamanager/core/common.py
mipi_datamanager/core/data_managers.py
mipi_datamanager/core/docs/__init__.py
mipi_datamanager/core/docs/contribute.py
mipi_datamanager/core/docs/getting_started.py
mipi_datamanager/core/docs/install.py
mipi_datamanager/core/docs/patch_notes.py
mipi_datamanager/core/docs/setup.py
mipi_datamanager/core/file_search.md
mipi_datamanager/core/file_search.py
mipi_datamanager/core/file_search.tcss
mipi_datamanager/core/file_search_gui.py
mipi_datamanager/core/jinja/__init__.py
mipi_datamanager/core/jinja/filters.py
mipi_datamanager/core/jinja/jinja.py
mipi_datamanager/core/meta.py
mipi_datamanager/core/read_setup.py
mipi_datamanager/core/templates/jinja_header.txt
mipi_datamanager/core/templates/jinja_repo_header.txt
mipi_datamanager/core/templates/mipi_summary.txt
mipi_datamanager/errors.py
mipi_datamanager/formatters.py
mipi_datamanager/generate_inserts.py
mipi_datamanager/query.py
mipi_datamanager/types.py
mipi_datamanager/wrangle.py
mipi_datamanager-1.4.8.dist-info/METADATA
mipi_datamanager-1.4.8.dist-info/WHEEL
mipi_datamanager-1.4.8.dist-info/entry_points.txt
mipi_datamanager-1.4.8.dist-info/RECORD
