Metadata-Version: 2.4
Name: mipi_datamanager
Version: 1.4.8
Summary: 
Author: murphy-sean1
Author-email: murphy-sean1@cooperhealth.edu
Requires-Python: >=3.12,<4.0
Classifier: Programming Language :: Python :: 3
Classifier: Programming Language :: Python :: 3.12
Classifier: Programming Language :: Python :: 3.13
Classifier: Programming Language :: Python :: 3.14
Requires-Dist: flask (>=3.0.3,<4.0.0)
Requires-Dist: flask-bcrypt (>=1.0.1,<2.0.0)
Requires-Dist: flask-restful (>=0.3.10,<0.4.0)
Requires-Dist: jinja2 (>=3.1.2,<4.0.0)
Requires-Dist: jinjasql2 (>=0.1.12,<0.2.0)
Requires-Dist: mkdocs (>=1.6.0,<2.0.0)
Requires-Dist: mkdocs-material (>=9.5.33,<10.0.0)
Requires-Dist: mkdocstrings[python] (>=0.26.1,<0.27.0)
Requires-Dist: openpyxl (>=3.1.5,<4.0.0)
Requires-Dist: pandas (>=2.2.2,<3.0.0)
Requires-Dist: pylint (>=3.3.3,<4.0.0)
Requires-Dist: pymdown-extensions (>=10.11.2,<11.0.0)
Requires-Dist: pyodbc (>=5.1.0,<6.0.0)
Requires-Dist: pytest (>=8.3.2,<9.0.0)
Requires-Dist: pytest-coverage (>=0.0,<0.1)
Requires-Dist: sqlalchemy (>=2.0.35,<3.0.0)
Requires-Dist: textual-dev (>=1.7.0,<2.0.0)
Requires-Dist: textual[syntax] (>=3.2.0,<4.0.0)
